pgesmd_self_access/__init__.py
pgesmd_self_access/api.py
pgesmd_self_access/helpers.py
pgesmd_self_access/pgesmd.py
pgesmd_self_access/server.py
pgesmd_self_access/test_api.py
pgesmd_self_access/test_helpers.py
pgesmd_self_access-0.0.6.dist-info/LICENSE
pgesmd_self_access-0.0.6.dist-info/METADATA
pgesmd_self_access-0.0.6.dist-info/WHEEL
pgesmd_self_access-0.0.6.dist-info/top_level.txt
pgesmd_self_access-0.0.6.dist-info/RECORD
