Metadata-Version: 2.1
Name: pgesmd-self-access
Version: 0.0.6
Summary: PG&E Share My Data API for Self Access users
Home-page: https://github.com/JPHutchins/pgesmd_self_access
Author: J.P. Hutchins
Author-email: jphutchins@gmail.com
License: UNKNOWN
Platform: UNKNOWN
Classifier: Programming Language :: Python :: 3
Classifier: License :: OSI Approved :: MIT License
Classifier: Operating System :: OS Independent
Requires-Python: >=3.8
Requires-Dist: pytz
Requires-Dist: requests
